editquality/__init__.py
editquality/about.py
editquality/config.py
editquality/editquality.py
editquality/codegen/__init__.py
editquality/codegen/generate.py
editquality/codegen/tests/__init__.py
editquality/codegen/tests/test_generate.py
editquality/feature_lists/__init__.py
editquality/feature_lists/arwiki.py
editquality/feature_lists/bnwiki.py
editquality/feature_lists/bswiki.py
editquality/feature_lists/cawiki.py
editquality/feature_lists/cswiki.py
editquality/feature_lists/dewiki.py
editquality/feature_lists/elwiki.py
editquality/feature_lists/enwiki.py
editquality/feature_lists/enwiktionary.py
editquality/feature_lists/eswiki.py
editquality/feature_lists/eswikibooks.py
editquality/feature_lists/eswikiquote.py
editquality/feature_lists/etwiki.py
editquality/feature_lists/fawiki.py
editquality/feature_lists/fiwiki.py
editquality/feature_lists/frwiki.py
editquality/feature_lists/glwiki.py
editquality/feature_lists/hewiki.py
editquality/feature_lists/hiwiki.py
editquality/feature_lists/hrwiki.py
editquality/feature_lists/huwiki.py
editquality/feature_lists/idwiki.py
editquality/feature_lists/iswiki.py
editquality/feature_lists/itwiki.py
editquality/feature_lists/jawiki.py
editquality/feature_lists/kowiki.py
editquality/feature_lists/lvwiki.py
editquality/feature_lists/mediawiki.py
editquality/feature_lists/nlwiki.py
editquality/feature_lists/nowiki.py
editquality/feature_lists/plwiki.py
editquality/feature_lists/ptwiki.py
editquality/feature_lists/rowiki.py
editquality/feature_lists/ruwiki.py
editquality/feature_lists/sqwiki.py
editquality/feature_lists/srwiki.py
editquality/feature_lists/svwiki.py
editquality/feature_lists/tawiki.py
editquality/feature_lists/translatewiki.py
editquality/feature_lists/trwiki.py
editquality/feature_lists/ukwiki.py
editquality/feature_lists/viwiki.py
editquality/feature_lists/wikibase.py
editquality/feature_lists/wikidatawiki.py
editquality/feature_lists/wikipedia.py
editquality/feature_lists/wikitext.py
editquality-0.5.1.dist-info/LICENSE
editquality-0.5.1.dist-info/METADATA
editquality-0.5.1.dist-info/WHEEL
editquality-0.5.1.dist-info/entry_points.txt
editquality-0.5.1.dist-info/top_level.txt
editquality-0.5.1.dist-info/RECORD
