Metadata-Version: 2.1
Name: editquality
Version: 0.5.1
Summary: A library for performing automatic detection of the quality of Wikipedia edits.
Home-page: https://github.com/wikimedia/editquality
Author: Aaron Halfaker
Author-email: ahalfaker@wikimedia.org
License: MIT
Classifier: Development Status :: 4 - Beta
Classifier: Topic :: Software Development :: Libraries :: Python Modules
Classifier: Programming Language :: Python
Classifier: Programming Language :: Python :: 3
Classifier: Intended Audience :: Developers
Classifier: License :: OSI Approved :: MIT License
Classifier: Operating System :: OS Independent
Classifier: Topic :: Utilities
Classifier: Topic :: Scientific/Engineering
License-File: LICENSE
Provides-Extra: dev
Requires-Dist: twine ; extra == 'dev'
